.DS_Store
bifrost/__init__.py
bifrost/actions.py
bifrost/apps.py
bifrost/asgi.py
bifrost/helpers.py
bifrost/models.py
bifrost/permissions.py
bifrost/registry.py
bifrost/relay.py
bifrost/schema.py
bifrost/settings.py
bifrost/signals.py
bifrost/urls.py
bifrost/utils.py
bifrost/views.py
bifrost/jwtauth/__init__.py
bifrost/jwtauth/schema.py
bifrost/migrations/0001_initial.py
bifrost/migrations/0002_stubmodel.py
bifrost/migrations/0003_delete_stubmodel.py
bifrost/migrations/__init__.py
bifrost/templates/__init__.py
bifrost/templates/bifrost/__init__.py
bifrost/templates/bifrost/graphiql.html
bifrost/templates/bifrost/playground.html
bifrost/templates/bifrost/preview.html
bifrost/types/__init__.py
bifrost/types/converters.py
bifrost/types/documents.py
bifrost/types/forms.py
bifrost/types/images.py
bifrost/types/media.py
bifrost/types/menus.py
bifrost/types/pages.py
bifrost/types/redirects.py
bifrost/types/search.py
bifrost/types/settings.py
bifrost/types/snippets.py
bifrost/types/streamfield.py
bifrost/types/structures.py
wagtail_bifrost-3.0.1.dist-info/METADATA
wagtail_bifrost-3.0.1.dist-info/WHEEL
wagtail_bifrost-3.0.1.dist-info/top_level.txt
wagtail_bifrost-3.0.1.dist-info/RECORD
