Metadata-Version: 2.1
Name: wagtail-bifrost
Version: 3.0.1
Summary: A django app that speeds up and simplifies implementing a GraphQL endoint!
Home-page: https://github.com/snek-shipyard/wagtail-bifrost
Author: Nico Schett
Author-email: nicoschett@icloud.com
License: UNKNOWN
Keywords: wagtail,django,graphene,graphql
Platform: UNKNOWN
Classifier: Development Status :: 4 - Beta
Classifier: Intended Audience :: Science/Research
Classifier: Programming Language :: Python :: 3.6
Classifier: Programming Language :: Python :: 3.7
Classifier: Programming Language :: Python :: 3.8
Classifier: Topic :: Scientific/Engineering
Requires-Python: >=3.6
Requires-Dist: Django (<3.2.0,>=3.1.0)
Requires-Dist: wagtail (<2.12.0,>=2.11.0)
Requires-Dist: graphene-django (==2.7.1)
Requires-Dist: graphql-core (==2.2.1)
Requires-Dist: channels (==2.4.0)
Requires-Dist: django-graphql-jwt (==0.3.1)
Requires-Dist: PyJWT (==1.7.1)
Requires-Dist: graphene-subscriptions
Requires-Dist: graphene-file-upload
Requires-Dist: wagtail-headless-preview
